[
    {
        "id": 1,
        "username": "kfvn",
        "titles": [
            "kfknfk",
            "fjbfj",
            "fbnfjb"
        ],
        "content": "fbnf",
        "status": "В процессе",
        "created": "2025-01-07 19:24:17.568170",
        "issue": "2000-02-02 00:00:00.000000"
    },
    {
        "id": 2,
        "username": "knvk",
        "titles": [
            "fknv",
            "ffknbkfbnf",
            "fkbnfkbn",
            "jvb"
        ],
        "content": "fnbfkbfjnbkrbvr",
        "status": "Новый статус",
        "created": "2025-01-07 19:25:06.086511",
        "issue": "3000-02-02 00:00:00.000000"
    },
    {
        "id": 3,
        "username": "Дима",
        "titles": [
            "тег1",
            "тест",
            "тег2"
        ],
        "content": "Тут будет содержимое заметки",
        "status": "Тестовый статус",
        "created": "2025-01-11 12:50:59.686694",
        "issue": "2025-02-10 00:00:00.000000"
    }
]